{"name":"YC","slug":"YC","count":1,"postlist":[{"title":"YAMC463 Handbook","uid":"9258d86cd64b6ec2774d92123ba0ae99","slug":"YAMC463","date":"2025-03-13T08:00:00.000Z","updated":"2025-03-13T10:36:43.642Z","comments":true,"path":"api/articles/YAMC463.json","keywords":null,"cover":null,"text":"YAMC463 Official Handbook IntroductionWelcome to YAMC463 Handbook, make sure you...","permalink":"/post/YAMC463","photos":[],"count_time":{"symbolsCount":544,"symbolsTime":"1 mins."},"categories":[],"tags":[{"name":"YAMC","slug":"YAMC","count":1,"path":"api/tags/YAMC.json"},{"name":"Y463","slug":"Y463","count":1,"path":"api/tags/Y463.json"},{"name":"YC","slug":"YC","count":1,"path":"api/tags/YC.json"}],"author":{"name":"匿名作者","slug":"blog-author","avatar":"/images/logo.png","link":"/","description":null,"socials":{"customs":null}},"feature":true}]}